weenect/__init__.py
weenect_gps_api-1.2.0.dist-info/METADATA
weenect_gps_api-1.2.0.dist-info/WHEEL
weenect_gps_api-1.2.0.dist-info/top_level.txt
weenect_gps_api-1.2.0.dist-info/RECORD
