Metadata-Version: 2.1
Name: weenect-gps-api
Version: 1.2.0
Summary: A package for accessing the Weenect-GPS api
Home-page: https://github.com/rsewell97/Weenect-GPS-requests
Author: Robbie Sewell
Author-email: rsewell97@gmail.com
License: UNKNOWN
Platform: UNKNOWN
Classifier: Programming Language :: Python :: 3
Classifier: License :: OSI Approved :: MIT License
Classifier: Operating System :: OS Independent
